design.sv
// Code your design here
`timescale 1ns/1ps

module mac(
  input wire sys_clock, sclr, load,
  input wire[3:0] a, b,
  output reg[3:0] product, sum, mac_out);
  
  always @ (a, b) begin
    product = a * b;
  end
  
  always @ (product, mac_out) begin
    sum = product + mac_out;
  end
  
  always @ (posedge sys_clock) begin
    if(sclr) mac_out <= 'b0;
    else if(load) mac_out <= sum;
  end
endmodule

testbench.sv
// Code your testbench here
// or browse Examples
`timescale 1ns/1ps

module mac_tb;
  reg sys_clock, sclr, load;
  reg[3:0] a, b;
  wire[3:0] product, sum, mac_out;
  
  mac uut(
    .sys_clock(sys_clock),
    .sclr(sclr),
    .load(load),
    .a(a),
    .b(b),
    .product(product),
    .sum(sum),
    .mac_out(mac_out));
  
  time clock_period = 100;
  
  initial begin
    sys_clock = 0;
    
    forever begin
      #(clock_period/2);
      sys_clock =~ sys_clock;
    end
  end
  
  initial begin
    sclr = 0; load = 0;
    
    fork
      forever begin
        #15360;
        sclr =~ sclr;
      end
      forever begin
        #30720;
        load =~ load;
      end
    join
  end
    
  initial begin
    a = 0; b = 0;

    fork
      forever begin
        #60;
        a = a + 1'b1;
      end
      forever begin
        #960;
        b = b + 1'b1;
      end
    join
  end
    
  time run_time = 61440;

  initial begin
    #run_time;
    $finish;
  end
  
  initial begin
    $dumpfile("dump.vcd");
    $dumpvars(0, mac_tb);
  end
endmodule

dump.vcd
$date
Thu Nov 19 11:19:02 2020
$end
$version
Riviera-PRO Version 2020.04.130.7729
$end
$timescale
1 ps
$end

$scope module mac_tb $end
$var wire 4 ! product [3:0] $end
$var wire 4 " sum [3:0] $end
$var wire 4 # mac_out [3:0] $end
$var reg 1 $ sys_clock $end
$var reg 1 % sclr $end
$var reg 1 & load $end
$var reg 4 ' a [3:0] $end
$var reg 4 ( b [3:0] $end
$var time 64 ) clock_period $end
$var time 64 * run_time $end

$scope module uut $end
$var wire 1 + sys_clock $end
$var wire 1 , sclr $end
$var wire 1 - load $end
$var wire 4 . a [3:0] $end
$var wire 4 / b [3:0] $end
$var reg 4 0 product [3:0] $end
$var reg 4 1 sum [3:0] $end
$var reg 4 2 mac_out [3:0] $end
$upscope $end


$scope task @FORK#35_0@ $end
$upscope $end


$scope task @FORK#39_1@ $end
$upscope $end


$scope task @FORK#50_2@ $end
$upscope $end


$scope task @FORK#54_3@ $end
$upscope $end

$upscope $end

$enddefinitions $end
$dumpvars
b0 !
bx "
bx #
0$
0%
0&
b0 '
b0 (
b1100100 )
b1111000000000000 *
0+
0,
0-
b0 .
b0 /
b0 0
bx 1
bx 2
$end
#50000
1$
1+
#60000
b1 '
b1 .
#100000
0$
0+
#120000
b10 '
b10 .
#150000
1$
1+
#180000
b11 '
b11 .
#200000
0$
0+
#240000
b100 '
b100 .
#250000
1$
1+
#300000
b101 '
0$
0+
b101 .
#350000
1$
1+
#360000
b110 '
b110 .
#400000
0$
0+
#420000
b111 '
b111 .
#450000
1$
1+
#480000
b1000 '
b1000 .
#500000
0$
0+
#540000
b1001 '
b1001 .
#550000
1$
1+
#600000
b1010 '
0$
0+
b1010 .
#650000
1$
1+
#660000
b1011 '
b1011 .
#700000
0$
0+
#720000
b1100 '
b1100 .
#750000
1$
1+
#780000
b1101 '
b1101 .
#800000
0$
0+
#840000
b1110 '
b1110 .
#850000
1$
1+
#900000
b1111 '
0$
0+
b1111 .
#950000
1$
1+
#960000
b1 (
b0 '
b0 .
b1 /
#1000000
0$
0+
#1020000
b1 '
b1 .
b1 0
b1 !
#1050000
1$
1+
#1080000
b10 '
b10 .
b10 0
b10 !
#1100000
0$
0+
#1140000
b11 '
b11 .
b11 0
b11 !
#1150000
1$
1+
#1200000
b100 '
0$
0+
b100 .
b100 0
b100 !
#1250000
1$
1+
#1260000
b101 '
b101 .
b101 0
b101 !
#1300000
0$
0+
#1320000
b110 '
b110 .
b110 0
b110 !
#1350000
1$
1+
#1380000
b111 '
b111 .
b111 0
b111 !
#1400000
0$
0+
#1440000
b1000 '
b1000 .
b1000 0
b1000 !
#1450000
1$
1+
#1500000
b1001 '
0$
0+
b1001 .
b1001 0
b1001 !
#1550000
1$
1+
#1560000
b1010 '
b1010 .
b1010 0
b1010 !
#1600000
0$
0+
#1620000
b1011 '
b1011 .
b1011 0
b1011 !
#1650000
1$
1+
#1680000
b1100 '
b1100 .
b1100 0
b1100 !
#1700000
0$
0+
#1740000
b1101 '
b1101 .
b1101 0
b1101 !
#1750000
1$
1+
#1800000
b1110 '
0$
0+
b1110 .
b1110 0
b1110 !
#1850000
1$
1+
#1860000
b1111 '
b1111 .
b1111 0
b1111 !
#1900000
0$
0+
#1920000
b10 (
b0 '
b0 .
b10 /
b0 0
b0 !
#1950000
1$
1+
#1980000
b1 '
b1 .
b10 0
b10 !
#2000000
0$
0+
#2040000
b10 '
b10 .
b100 0
b100 !
#2050000
1$
1+
#2100000
b11 '
0$
0+
b11 .
b110 0
b110 !
#2150000
1$
1+
#2160000
b100 '
b100 .
b1000 0
b1000 !
#2200000
0$
0+
#2220000
b101 '
b101 .
b1010 0
b1010 !
#2250000
1$
1+
#2280000
b110 '
b110 .
b1100 0
b1100 !
#2300000
0$
0+
#2340000
b111 '
b111 .
b1110 0
b1110 !
#2350000
1$
1+
#2400000
b1000 '
0$
0+
b1000 .
b0 0
b0 !
#2450000
1$
1+
#2460000
b1001 '
b1001 .
b10 0
b10 !
#2500000
0$
0+
#2520000
b1010 '
b1010 .
b100 0
b100 !
#2550000
1$
1+
#2580000
b1011 '
b1011 .
b110 0
b110 !
#2600000
0$
0+
#2640000
b1100 '
b1100 .
b1000 0
b1000 !
#2650000
1$
1+
#2700000
b1101 '
0$
0+
b1101 .
b1010 0
b1010 !
#2750000
1$
1+
#2760000
b1110 '
b1110 .
b1100 0
b1100 !
#2800000
0$
0+
#2820000
b1111 '
b1111 .
b1110 0
b1110 !
#2850000
1$
1+
#2880000
b11 (
b0 '
b0 .
b11 /
b0 0
b0 !
#2900000
0$
0+
#2940000
b1 '
b1 .
b11 0
b11 !
#2950000
1$
1+
#3000000
b10 '
0$
0+
b10 .
b110 0
b110 !
#3050000
1$
1+
#3060000
b11 '
b11 .
b1001 0
b1001 !
#3100000
0$
0+
#3120000
b100 '
b100 .
b1100 0
b1100 !
#3150000
1$
1+
#3180000
b101 '
b101 .
b1111 0
b1111 !
#3200000
0$
0+
#3240000
b110 '
b110 .
b10 0
b10 !
#3250000
1$
1+
#3300000
b111 '
0$
0+
b111 .
b101 0
b101 !
#3350000
1$
1+
#3360000
b1000 '
b1000 .
b1000 0
b1000 !
#3400000
0$
0+
#3420000
b1001 '
b1001 .
b1011 0
b1011 !
#3450000
1$
1+
#3480000
b1010 '
b1010 .
b1110 0
b1110 !
#3500000
0$
0+
#3540000
b1011 '
b1011 .
b1 0
b1 !
#3550000
1$
1+
#3600000
b1100 '
0$
0+
b1100 .
b100 0
b100 !
#3650000
1$
1+
#3660000
b1101 '
b1101 .
b111 0
b111 !
#3700000
0$
0+
#3720000
b1110 '
b1110 .
b1010 0
b1010 !
#3750000
1$
1+
#3780000
b1111 '
b1111 .
b1101 0
b1101 !
#3800000
0$
0+
#3840000
b100 (
b0 '
b0 .
b100 /
b0 0
b0 !
#3850000
1$
1+
#3900000
b1 '
0$
0+
b1 .
b100 0
b100 !
#3950000
1$
1+
#3960000
b10 '
b10 .
b1000 0
b1000 !
#4000000
0$
0+
#4020000
b11 '
b11 .
b1100 0
b1100 !
#4050000
1$
1+
#4080000
b100 '
b100 .
b0 0
b0 !
#4100000
0$
0+
#4140000
b101 '
b101 .
b100 0
b100 !
#4150000
1$
1+
#4200000
b110 '
0$
0+
b110 .
b1000 0
b1000 !
#4250000
1$
1+
#4260000
b111 '
b111 .
b1100 0
b1100 !
#4300000
0$
0+
#4320000
b1000 '
b1000 .
b0 0
b0 !
#4350000
1$
1+
#4380000
b1001 '
b1001 .
b100 0
b100 !
#4400000
0$
0+
#4440000
b1010 '
b1010 .
b1000 0
b1000 !
#4450000
1$
1+
#4500000
b1011 '
0$
0+
b1011 .
b1100 0
b1100 !
#4550000
1$
1+
#4560000
b1100 '
b1100 .
b0 0
b0 !
#4600000
0$
0+
#4620000
b1101 '
b1101 .
b100 0
b100 !
#4650000
1$
1+
#4680000
b1110 '
b1110 .
b1000 0
b1000 !
#4700000
0$
0+
#4740000
b1111 '
b1111 .
b1100 0
b1100 !
#4750000
1$
1+
#4800000
b101 (
b0 '
0$
0+
b0 .
b101 /
b0 0
b0 !
#4850000
1$
1+
#4860000
b1 '
b1 .
b101 0
b101 !
#4900000
0$
0+
#4920000
b10 '
b10 .
b1010 0
b1010 !
#4950000
1$
1+
#4980000
b11 '
b11 .
b1111 0
b1111 !
#5000000
0$
0+
#5040000
b100 '
b100 .
b100 0
b100 !
#5050000
1$
1+
#5100000
b101 '
0$
0+
b101 .
b1001 0
b1001 !
#5150000
1$
1+
#5160000
b110 '
b110 .
b1110 0
b1110 !
#5200000
0$
0+
#5220000
b111 '
b111 .
b11 0
b11 !
#5250000
1$
1+
#5280000
b1000 '
b1000 .
b1000 0
b1000 !
#5300000
0$
0+
#5340000
b1001 '
b1001 .
b1101 0
b1101 !
#5350000
1$
1+
#5400000
b1010 '
0$
0+
b1010 .
b10 0
b10 !
#5450000
1$
1+
#5460000
b1011 '
b1011 .
b111 0
b111 !
#5500000
0$
0+
#5520000
b1100 '
b1100 .
b1100 0
b1100 !
#5550000
1$
1+
#5580000
b1101 '
b1101 .
b1 0
b1 !
#5600000
0$
0+
#5640000
b1110 '
b1110 .
b110 0
b110 !
#5650000
1$
1+
#5700000
b1111 '
0$
0+
b1111 .
b1011 0
b1011 !
#5750000
1$
1+
#5760000
b110 (
b0 '
b0 .
b110 /
b0 0
b0 !
#5800000
0$
0+
#5820000
b1 '
b1 .
b110 0
b110 !
#5850000
1$
1+
#5880000
b10 '
b10 .
b1100 0
b1100 !
#5900000
0$
0+
#5940000
b11 '
b11 .
b10 0
b10 !
#5950000
1$
1+
#6000000
b100 '
0$
0+
b100 .
b1000 0
b1000 !
#6050000
1$
1+
#6060000
b101 '
b101 .
b1110 0
b1110 !
#6100000
0$
0+
#6120000
b110 '
b110 .
b100 0
b100 !
#6150000
1$
1+
#6180000
b111 '
b111 .
b1010 0
b1010 !
#6200000
0$
0+
#6240000
b1000 '
b1000 .
b0 0
b0 !
#6250000
1$
1+
#6300000
b1001 '
0$
0+
b1001 .
b110 0
b110 !
#6350000
1$
1+
#6360000
b1010 '
b1010 .
b1100 0
b1100 !
#6400000
0$
0+
#6420000
b1011 '
b1011 .
b10 0
b10 !
#6450000
1$
1+
#6480000
b1100 '
b1100 .
b1000 0
b1000 !
#6500000
0$
0+
#6540000
b1101 '
b1101 .
b1110 0
b1110 !
#6550000
1$
1+
#6600000
b1110 '
0$
0+
b1110 .
b100 0
b100 !
#6650000
1$
1+
#6660000
b1111 '
b1111 .
b1010 0
b1010 !
#6700000
0$
0+
#6720000
b111 (
b0 '
b0 .
b111 /
b0 0
b0 !
#6750000
1$
1+
#6780000
b1 '
b1 .
b111 0
b111 !
#6800000
0$
0+
#6840000
b10 '
b10 .
b1110 0
b1110 !
#6850000
1$
1+
#6900000
b11 '
0$
0+
b11 .
b101 0
b101 !
#6950000
1$
1+
#6960000
b100 '
b100 .
b1100 0
b1100 !
#7000000
0$
0+
#7020000
b101 '
b101 .
b11 0
b11 !
#7050000
1$
1+
#7080000
b110 '
b110 .
b1010 0
b1010 !
#7100000
0$
0+
#7140000
b111 '
b111 .
b1 0
b1 !
#7150000
1$
1+
#7200000
b1000 '
0$
0+
b1000 .
b1000 0
b1000 !
#7250000
1$
1+
#7260000
b1001 '
b1001 .
b1111 0
b1111 !
#7300000
0$
0+
#7320000
b1010 '
b1010 .
b110 0
b110 !
#7350000
1$
1+
#7380000
b1011 '
b1011 .
b1101 0
b1101 !
#7400000
0$
0+
#7440000
b1100 '
b1100 .
b100 0
b100 !
#7450000
1$
1+
#7500000
b1101 '
0$
0+
b1101 .
b1011 0
b1011 !
#7550000
1$
1+
#7560000
b1110 '
b1110 .
b10 0
b10 !
#7600000
0$
0+
#7620000
b1111 '
b1111 .
b1001 0
b1001 !
#7650000
1$
1+
#7680000
b1000 (
b0 '
b0 .
b1000 /
b0 0
b0 !
#7700000
0$
0+
#7740000
b1 '
b1 .
b1000 0
b1000 !
#7750000
1$
1+
#7800000
b10 '
0$
0+
b10 .
b0 0
b0 !
#7850000
1$
1+
#7860000
b11 '
b11 .
b1000 0
b1000 !
#7900000
0$
0+
#7920000
b100 '
b100 .
b0 0
b0 !
#7950000
1$
1+
#7980000
b101 '
b101 .
b1000 0
b1000 !
#8000000
0$
0+
#8040000
b110 '
b110 .
b0 0
b0 !
#8050000
1$
1+
#8100000
b111 '
0$
0+
b111 .
b1000 0
b1000 !
#8150000
1$
1+
#8160000
b1000 '
b1000 .
b0 0
b0 !
#8200000
0$
0+
#8220000
b1001 '
b1001 .
b1000 0
b1000 !
#8250000
1$
1+
#8280000
b1010 '
b1010 .
b0 0
b0 !
#8300000
0$
0+
#8340000
b1011 '
b1011 .
b1000 0
b1000 !
#8350000
1$
1+
#8400000
b1100 '
0$
0+
b1100 .
b0 0
b0 !
#8450000
1$
1+
#8460000
b1101 '
b1101 .
b1000 0
b1000 !
#8500000
0$
0+
#8520000
b1110 '
b1110 .
b0 0
b0 !
#8550000
1$
1+
#8580000
b1111 '
b1111 .
b1000 0
b1000 !
#8600000
0$
0+
#8640000
b1001 (
b0 '
b0 .
b1001 /
b0 0
b0 !
#8650000
1$
1+
#8700000
b1 '
0$
0+
b1 .
b1001 0
b1001 !
#8750000
1$
1+
#8760000
b10 '
b10 .
b10 0
b10 !
#8800000
0$
0+
#8820000
b11 '
b11 .
b1011 0
b1011 !
#8850000
1$
1+
#8880000
b100 '
b100 .
b100 0
b100 !
#8900000
0$
0+
#8940000
b101 '
b101 .
b1101 0
b1101 !
#8950000
1$
1+
#9000000
b110 '
0$
0+
b110 .
b110 0
b110 !
#9050000
1$
1+
#9060000
b111 '
b111 .
b1111 0
b1111 !
#9100000
0$
0+
#9120000
b1000 '
b1000 .
b1000 0
b1000 !
#9150000
1$
1+
#9180000
b1001 '
b1001 .
b1 0
b1 !
#9200000
0$
0+
#9240000
b1010 '
b1010 .
b1010 0
b1010 !
#9250000
1$
1+
#9300000
b1011 '
0$
0+
b1011 .
b11 0
b11 !
#9350000
1$
1+
#9360000
b1100 '
b1100 .
b1100 0
b1100 !
#9400000
0$
0+
#9420000
b1101 '
b1101 .
b101 0
b101 !
#9450000
1$
1+
#9480000
b1110 '
b1110 .
b1110 0
b1110 !
#9500000
0$
0+
#9540000
b1111 '
b1111 .
b111 0
b111 !
#9550000
1$
1+
#9600000
b1010 (
b0 '
0$
0+
b0 .
b1010 /
b0 0
b0 !
#9650000
1$
1+
#9660000
b1 '
b1 .
b1010 0
b1010 !
#9700000
0$
0+
#9720000
b10 '
b10 .
b100 0
b100 !
#9750000
1$
1+
#9780000
b11 '
b11 .
b1110 0
b1110 !
#9800000
0$
0+
#9840000
b100 '
b100 .
b1000 0
b1000 !
#9850000
1$
1+
#9900000
b101 '
0$
0+
b101 .
b10 0
b10 !
#9950000
1$
1+
#9960000
b110 '
b110 .
b1100 0
b1100 !
#10000000
0$
0+
#10020000
b111 '
b111 .
b110 0
b110 !
#10050000
1$
1+
#10080000
b1000 '
b1000 .
b0 0
b0 !
#10100000
0$
0+
#10140000
b1001 '
b1001 .
b1010 0
b1010 !
#10150000
1$
1+
#10200000
b1010 '
0$
0+
b1010 .
b100 0
b100 !
#10250000
1$
1+
#10260000
b1011 '
b1011 .
b1110 0
b1110 !
#10300000
0$
0+
#10320000
b1100 '
b1100 .
b1000 0
b1000 !
#10350000
1$
1+
#10380000
b1101 '
b1101 .
b10 0
b10 !
#10400000
0$
0+
#10440000
b1110 '
b1110 .
b1100 0
b1100 !
#10450000
1$
1+
#10500000
b1111 '
0$
0+
b1111 .
b110 0
b110 !
#10550000
1$
1+
#10560000
b1011 (
b0 '
b0 .
b1011 /
b0 0
b0 !
#10600000
0$
0+
#10620000
b1 '
b1 .
b1011 0
b1011 !
#10650000
1$
1+
#10680000
b10 '
b10 .
b110 0
b110 !
#10700000
0$
0+
#10740000
b11 '
b11 .
b1 0
b1 !
#10750000
1$
1+
#10800000
b100 '
0$
0+
b100 .
b1100 0
b1100 !
#10850000
1$
1+
#10860000
b101 '
b101 .
b111 0
b111 !
#10900000
0$
0+
#10920000
b110 '
b110 .
b10 0
b10 !
#10950000
1$
1+
#10980000
b111 '
b111 .
b1101 0
b1101 !
#11000000
0$
0+
#11040000
b1000 '
b1000 .
b1000 0
b1000 !
#11050000
1$
1+
#11100000
b1001 '
0$
0+
b1001 .
b11 0
b11 !
#11150000
1$
1+
#11160000
b1010 '
b1010 .
b1110 0
b1110 !
#11200000
0$
0+
#11220000
b1011 '
b1011 .
b1001 0
b1001 !
#11250000
1$
1+
#11280000
b1100 '
b1100 .
b100 0
b100 !
#11300000
0$
0+
#11340000
b1101 '
b1101 .
b1111 0
b1111 !
#11350000
1$
1+
#11400000
b1110 '
0$
0+
b1110 .
b1010 0
b1010 !
#11450000
1$
1+
#11460000
b1111 '
b1111 .
b101 0
b101 !
#11500000
0$
0+
#11520000
b1100 (
b0 '
b0 .
b1100 /
b0 0
b0 !
#11550000
1$
1+
#11580000
b1 '
b1 .
b1100 0
b1100 !
#11600000
0$
0+
#11640000
b10 '
b10 .
b1000 0
b1000 !
#11650000
1$
1+
#11700000
b11 '
0$
0+
b11 .
b100 0
b100 !
#11750000
1$
1+
#11760000
b100 '
b100 .
b0 0
b0 !
#11800000
0$
0+
#11820000
b101 '
b101 .
b1100 0
b1100 !
#11850000
1$
1+
#11880000
b110 '
b110 .
b1000 0
b1000 !
#11900000
0$
0+
#11940000
b111 '
b111 .
b100 0
b100 !
#11950000
1$
1+
#12000000
b1000 '
0$
0+
b1000 .
b0 0
b0 !
#12050000
1$
1+
#12060000
b1001 '
b1001 .
b1100 0
b1100 !
#12100000
0$
0+
#12120000
b1010 '
b1010 .
b1000 0
b1000 !
#12150000
1$
1+
#12180000
b1011 '
b1011 .
b100 0
b100 !
#12200000
0$
0+
#12240000
b1100 '
b1100 .
b0 0
b0 !
#12250000
1$
1+
#12300000
b1101 '
0$
0+
b1101 .
b1100 0
b1100 !
#12350000
1$
1+
#12360000
b1110 '
b1110 .
b1000 0
b1000 !
#12400000
0$
0+
#12420000
b1111 '
b1111 .
b100 0
b100 !
#12450000
1$
1+
#12480000
b1101 (
b0 '
b0 .
b1101 /
b0 0
b0 !
#12500000
0$
0+
#12540000
b1 '
b1 .
b1101 0
b1101 !
#12550000
1$
1+
#12600000
b10 '
0$
0+
b10 .
b1010 0
b1010 !
#12650000
1$
1+
#12660000
b11 '
b11 .
b111 0
b111 !
#12700000
0$
0+
#12720000
b100 '
b100 .
b100 0
b100 !
#12750000
1$
1+
#12780000
b101 '
b101 .
b1 0
b1 !
#12800000
0$
0+
#12840000
b110 '
b110 .
b1110 0
b1110 !
#12850000
1$
1+
#12900000
b111 '
0$
0+
b111 .
b1011 0
b1011 !
#12950000
1$
1+
#12960000
b1000 '
b1000 .
b1000 0
b1000 !
#13000000
0$
0+
#13020000
b1001 '
b1001 .
b101 0
b101 !
#13050000
1$
1+
#13080000
b1010 '
b1010 .
b10 0
b10 !
#13100000
0$
0+
#13140000
b1011 '
b1011 .
b1111 0
b1111 !
#13150000
1$
1+
#13200000
b1100 '
0$
0+
b1100 .
b1100 0
b1100 !
#13250000
1$
1+
#13260000
b1101 '
b1101 .
b1001 0
b1001 !
#13300000
0$
0+
#13320000
b1110 '
b1110 .
b110 0
b110 !
#13350000
1$
1+
#13380000
b1111 '
b1111 .
b11 0
b11 !
#13400000
0$
0+
#13440000
b1110 (
b0 '
b0 .
b1110 /
b0 0
b0 !
#13450000
1$
1+
#13500000
b1 '
0$
0+
b1 .
b1110 0
b1110 !
#13550000
1$
1+
#13560000
b10 '
b10 .
b1100 0
b1100 !
#13600000
0$
0+
#13620000
b11 '
b11 .
b1010 0
b1010 !
#13650000
1$
1+
#13680000
b100 '
b100 .
b1000 0
b1000 !
#13700000
0$
0+
#13740000
b101 '
b101 .
b110 0
b110 !
#13750000
1$
1+
#13800000
b110 '
0$
0+
b110 .
b100 0
b100 !
#13850000
1$
1+
#13860000
b111 '
b111 .
b10 0
b10 !
#13900000
0$
0+
#13920000
b1000 '
b1000 .
b0 0
b0 !
#13950000
1$
1+
#13980000
b1001 '
b1001 .
b1110 0
b1110 !
#14000000
0$
0+
#14040000
b1010 '
b1010 .
b1100 0
b1100 !
#14050000
1$
1+
#14100000
b1011 '
0$
0+
b1011 .
b1010 0
b1010 !
#14150000
1$
1+
#14160000
b1100 '
b1100 .
b1000 0
b1000 !
#14200000
0$
0+
#14220000
b1101 '
b1101 .
b110 0
b110 !
#14250000
1$
1+
#14280000
b1110 '
b1110 .
b100 0
b100 !
#14300000
0$
0+
#14340000
b1111 '
b1111 .
b10 0
b10 !
#14350000
1$
1+
#14400000
b1111 (
b0 '
0$
0+
b0 .
b1111 /
b0 0
b0 !
#14450000
1$
1+
#14460000
b1 '
b1 .
b1111 0
b1111 !
#14500000
0$
0+
#14520000
b10 '
b10 .
b1110 0
b1110 !
#14550000
1$
1+
#14580000
b11 '
b11 .
b1101 0
b1101 !
#14600000
0$
0+
#14640000
b100 '
b100 .
b1100 0
b1100 !
#14650000
1$
1+
#14700000
b101 '
0$
0+
b101 .
b1011 0
b1011 !
#14750000
1$
1+
#14760000
b110 '
b110 .
b1010 0
b1010 !
#14800000
0$
0+
#14820000
b111 '
b111 .
b1001 0
b1001 !
#14850000
1$
1+
#14880000
b1000 '
b1000 .
b1000 0
b1000 !
#14900000
0$
0+
#14940000
b1001 '
b1001 .
b111 0
b111 !
#14950000
1$
1+
#15000000
b1010 '
0$
0+
b1010 .
b110 0
b110 !
#15050000
1$
1+
#15060000
b1011 '
b1011 .
b101 0
b101 !
#15100000
0$
0+
#15120000
b1100 '
b1100 .
b100 0
b100 !
#15150000
1$
1+
#15180000
b1101 '
b1101 .
b11 0
b11 !
#15200000
0$
0+
#15240000
b1110 '
b1110 .
b10 0
b10 !
#15250000
1$
1+
#15300000
b1111 '
0$
0+
b1111 .
b1 0
b1 !
#15350000
1$
1+
#15360000
1%
b0 (
b0 '
b0 .
b0 /
1,
b0 0
b0 !
#15400000
0$
0+
#15420000
b1 '
b1 .
#15450000
1$
1+
b0 2
b0 #
b0 1
b0 "
#15480000
b10 '
b10 .
#15500000
0$
0+
#15540000
b11 '
b11 .
#15550000
1$
1+
#15600000
b100 '
0$
0+
b100 .
#15650000
1$
1+
#15660000
b101 '
b101 .
#15700000
0$
0+
#15720000
b110 '
b110 .
#15750000
1$
1+
#15780000
b111 '
b111 .
#15800000
0$
0+
#15840000
b1000 '
b1000 .
#15850000
1$
1+
#15900000
b1001 '
0$
0+
b1001 .
#15950000
1$
1+
#15960000
b1010 '
b1010 .
#16000000
0$
0+
#16020000
b1011 '
b1011 .
#16050000
1$
1+
#16080000
b1100 '
b1100 .
#16100000
0$
0+
#16140000
b1101 '
b1101 .
#16150000
1$
1+
#16200000
b1110 '
0$
0+
b1110 .
#16250000
1$
1+
#16260000
b1111 '
b1111 .
#16300000
0$
0+
#16320000
b1 (
b0 '
b0 .
b1 /
#16350000
1$
1+
#16380000
b1 '
b1 .
b1 0
b1 !
b1 1
b1 "
#16400000
0$
0+
#16440000
b10 '
b10 .
b10 0
b10 !
b10 1
b10 "
#16450000
1$
1+
#16500000
b11 '
0$
0+
b11 .
b11 0
b11 !
b11 1
b11 "
#16550000
1$
1+
#16560000
b100 '
b100 .
b100 0
b100 !
b100 1
b100 "
#16600000
0$
0+
#16620000
b101 '
b101 .
b101 0
b101 !
b101 1
b101 "
#16650000
1$
1+
#16680000
b110 '
b110 .
b110 0
b110 !
b110 1
b110 "
#16700000
0$
0+
#16740000
b111 '
b111 .
b111 0
b111 !
b111 1
b111 "
#16750000
1$
1+
#16800000
b1000 '
0$
0+
b1000 .
b1000 0
b1000 !
b1000 1
b1000 "
#16850000
1$
1+
#16860000
b1001 '
b1001 .
b1001 0
b1001 !
b1001 1
b1001 "
#16900000
0$
0+
#16920000
b1010 '
b1010 .
b1010 0
b1010 !
b1010 1
b1010 "
#16950000
1$
1+
#16980000
b1011 '
b1011 .
b1011 0
b1011 !
b1011 1
b1011 "
#17000000
0$
0+
#17040000
b1100 '
b1100 .
b1100 0
b1100 !
b1100 1
b1100 "
#17050000
1$
1+
#17100000
b1101 '
0$
0+
b1101 .
b1101 0
b1101 !
b1101 1
b1101 "
#17150000
1$
1+
#17160000
b1110 '
b1110 .
b1110 0
b1110 !
b1110 1
b1110 "
#17200000
0$
0+
#17220000
b1111 '
b1111 .
b1111 0
b1111 !
b1111 1
b1111 "
#17250000
1$
1+
#17280000
b10 (
b0 '
b0 .
b10 /
b0 0
b0 !
b0 1
b0 "
#17300000
0$
0+
#17340000
b1 '
b1 .
b10 0
b10 !
b10 1
b10 "
#17350000
1$
1+
#17400000
b10 '
0$
0+
b10 .
b100 0
b100 !
b100 1
b100 "
#17450000
1$
1+
#17460000
b11 '
b11 .
b110 0
b110 !
b110 1
b110 "
#17500000
0$
0+
#17520000
b100 '
b100 .
b1000 0
b1000 !
b1000 1
b1000 "
#17550000
1$
1+
#17580000
b101 '
b101 .
b1010 0
b1010 !
b1010 1
b1010 "
#17600000
0$
0+
#17640000
b110 '
b110 .
b1100 0
b1100 !
b1100 1
b1100 "
#17650000
1$
1+
#17700000
b111 '
0$
0+
b111 .
b1110 0
b1110 !
b1110 1
b1110 "
#17750000
1$
1+
#17760000
b1000 '
b1000 .
b0 0
b0 !
b0 1
b0 "
#17800000
0$
0+
#17820000
b1001 '
b1001 .
b10 0
b10 !
b10 1
b10 "
#17850000
1$
1+
#17880000
b1010 '
b1010 .
b100 0
b100 !
b100 1
b100 "
#17900000
0$
0+
#17940000
b1011 '
b1011 .
b110 0
b110 !
b110 1
b110 "
#17950000
1$
1+
#18000000
b1100 '
0$
0+
b1100 .
b1000 0
b1000 !
b1000 1
b1000 "
#18050000
1$
1+
#18060000
b1101 '
b1101 .
b1010 0
b1010 !
b1010 1
b1010 "
#18100000
0$
0+
#18120000
b1110 '
b1110 .
b1100 0
b1100 !
b1100 1
b1100 "
#18150000
1$
1+
#18180000
b1111 '
b1111 .
b1110 0
b1110 !
b1110 1
b1110 "
#18200000
0$
0+
#18240000
b11 (
b0 '
b0 .
b11 /
b0 0
b0 !
b0 1
b0 "
#18250000
1$
1+
#18300000
b1 '
0$
0+
b1 .
b11 0
b11 !
b11 1
b11 "
#18350000
1$
1+
#18360000
b10 '
b10 .
b110 0
b110 !
b110 1
b110 "
#18400000
0$
0+
#18420000
b11 '
b11 .
b1001 0
b1001 !
b1001 1
b1001 "
#18450000
1$
1+
#18480000
b100 '
b100 .
b1100 0
b1100 !
b1100 1
b1100 "
#18500000
0$
0+
#18540000
b101 '
b101 .
b1111 0
b1111 !
b1111 1
b1111 "
#18550000
1$
1+
#18600000
b110 '
0$
0+
b110 .
b10 0
b10 !
b10 1
b10 "
#18650000
1$
1+
#18660000
b111 '
b111 .
b101 0
b101 !
b101 1
b101 "
#18700000
0$
0+
#18720000
b1000 '
b1000 .
b1000 0
b1000 !
b1000 1
b1000 "
#18750000
1$
1+
#18780000
b1001 '
b1001 .
b1011 0
b1011 !
b1011 1
b1011 "
#18800000
0$
0+
#18840000
b1010 '
b1010 .
b1110 0
b1110 !
b1110 1
b1110 "
#18850000
1$
1+
#18900000
b1011 '
0$
0+
b1011 .
b1 0
b1 !
b1 1
b1 "
#18950000
1$
1+
#18960000
b1100 '
b1100 .
b100 0
b100 !
b100 1
b100 "
#19000000
0$
0+
#19020000
b1101 '
b1101 .
b111 0
b111 !
b111 1
b111 "
#19050000
1$
1+
#19080000
b1110 '
b1110 .
b1010 0
b1010 !
b1010 1
b1010 "
#19100000
0$
0+
#19140000
b1111 '
b1111 .
b1101 0
b1101 !
b1101 1
b1101 "
#19150000
1$
1+
#19200000
b100 (
b0 '
0$
0+
b0 .
b100 /
b0 0
b0 !
b0 1
b0 "
#19250000
1$
1+
#19260000
b1 '
b1 .
b100 0
b100 !
b100 1
b100 "
#19300000
0$
0+
#19320000
b10 '
b10 .
b1000 0
b1000 !
b1000 1
b1000 "
#19350000
1$
1+
#19380000
b11 '
b11 .
b1100 0
b1100 !
b1100 1
b1100 "
#19400000
0$
0+
#19440000
b100 '
b100 .
b0 0
b0 !
b0 1
b0 "
#19450000
1$
1+
#19500000
b101 '
0$
0+
b101 .
b100 0
b100 !
b100 1
b100 "
#19550000
1$
1+
#19560000
b110 '
b110 .
b1000 0
b1000 !
b1000 1
b1000 "
#19600000
0$
0+
#19620000
b111 '
b111 .
b1100 0
b1100 !
b1100 1
b1100 "
#19650000
1$
1+
#19680000
b1000 '
b1000 .
b0 0
b0 !
b0 1
b0 "
#19700000
0$
0+
#19740000
b1001 '
b1001 .
b100 0
b100 !
b100 1
b100 "
#19750000
1$
1+
#19800000
b1010 '
0$
0+
b1010 .
b1000 0
b1000 !
b1000 1
b1000 "
#19850000
1$
1+
#19860000
b1011 '
b1011 .
b1100 0
b1100 !
b1100 1
b1100 "
#19900000
0$
0+
#19920000
b1100 '
b1100 .
b0 0
b0 !
b0 1
b0 "
#19950000
1$
1+
#19980000
b1101 '
b1101 .
b100 0
b100 !
b100 1
b100 "
#20000000
0$
0+
#20040000
b1110 '
b1110 .
b1000 0
b1000 !
b1000 1
b1000 "
#20050000
1$
1+
#20100000
b1111 '
0$
0+
b1111 .
b1100 0
b1100 !
b1100 1
b1100 "
#20150000
1$
1+
